mode_rag/__init__.py
mode_rag/inference/__init__.py
mode_rag/inference/find_cluster.py
mode_rag/inference/main.py
mode_rag/inference/model.py
mode_rag/inference/search.py
mode_rag/inference/types.py
mode_rag/ingestion/__init__.py
mode_rag/ingestion/centroid.py
mode_rag/ingestion/cluster.py
mode_rag/ingestion/main.py
mode_rag/utils/__init__.py
mode_rag/utils/chunker.py
mode_rag/utils/data.py
mode_rag/utils/embedding.py
mode_rag-1.0.3.dist-info/LICENSE
mode_rag-1.0.3.dist-info/METADATA
mode_rag-1.0.3.dist-info/WHEEL
mode_rag-1.0.3.dist-info/RECORD
