Metadata-Version: 2.3
Name: mode_rag
Version: 1.0.3
Summary: MODE organizes documents into semantically coherent clusters and uses centroid-based retrieval to deliver scalable, efficient, and interpretable Retrieval-Augmented Generation without relying on large vector databases.
License: MIT
Author: Rahul Anand rahulanand1103@gmail.com
Requires-Python: >=3.9,<4.0
Classifier: License :: OSI Approved :: MIT License
Classifier: Operating System :: OS Independent
Classifier: Programming Language :: Python :: 3
Classifier: Programming Language :: Python :: 3.9
Classifier: Programming Language :: Python :: 3.10
Classifier: Programming Language :: Python :: 3.11
Classifier: Programming Language :: Python :: 3.12
Classifier: Programming Language :: Python :: 3.13
Requires-Dist: hdbscan (==0.8.40)
Requires-Dist: litellm (==1.54.0)
Requires-Dist: torch (==2.4.1)
